AoUPRS/__init__.py
AoUPRS/calculate_prs.py
AoUPRS/calculate_prs_mt.py
AoUPRS/calculate_prs_vds.py
AoUPRS/prepare.py
AoUPRS/utils.py
aouprs-0.2.6.dist-info/licenses/LICENSE
aouprs-0.2.6.dist-info/METADATA
aouprs-0.2.6.dist-info/WHEEL
aouprs-0.2.6.dist-info/top_level.txt
aouprs-0.2.6.dist-info/RECORD
