Metadata-Version: 2.4
Name: AoUPRS
Version: 0.2.6
Summary: AoUPRS is a Python module for calculating Polygenic Risk Scores (PRS) specific to the All of Us study
Home-page: https://github.com/AhmedMKhattab/AoUPRS
Author: Ahmed Khattab
License-File: LICENSE
Requires-Dist: hail
Requires-Dist: gcsfs
Requires-Dist: pandas
Dynamic: author
Dynamic: description
Dynamic: description-content-type
Dynamic: home-page
Dynamic: license-file
Dynamic: requires-dist
Dynamic: summary
